__init__.py
setup.py
grape_chem/__init__.py
grape_chem/analysis/__init__.py
grape_chem/analysis/_classyfire.py
grape_chem/analysis/summarize.py
grape_chem/datasets/FreeSolv_dataset.py
grape_chem/datasets/QM9_dataset.py
grape_chem/datasets/__init__.py
grape_chem/datasets/jean_claude_bradley_double_plus.py
grape_chem/datasets/logP_dataset.py
grape_chem/models/AFP_gnn.py
grape_chem/models/DMPNN_gnn.py
grape_chem/models/MEGNet_gnn.py
grape_chem/models/MPNN_gnn.py
grape_chem/models/Weave_gnn.py
grape_chem/models/__init__.py
grape_chem/models/test_models.py
grape_chem/plots/__init__.py
grape_chem/plots/analysis_plots.py
grape_chem/plots/pca_plot.py
grape_chem/plots/post_plots.py
grape_chem/plots/tSNE.py
grape_chem/plots/williamsplot.py
grape_chem/splits/__init__.py
grape_chem/splits/butina_splits.py
grape_chem/utils/__init__.py
grape_chem/utils/data.py
grape_chem/utils/feature_func.py
grape_chem/utils/featurizer.py
grape_chem/utils/model_utils.py
grape_chem/utils/plot_utils.py
grape_chem/utils/split_utils.py
grape_chem-1.0.4.dist-info/LICENSE
grape_chem-1.0.4.dist-info/METADATA
grape_chem-1.0.4.dist-info/WHEEL
grape_chem-1.0.4.dist-info/top_level.txt
grape_chem-1.0.4.dist-info/RECORD
